persistent_cache/__init__.py
persistent_cache/__main__.py
persistent_cache/_version.py
persistent_cache/cli.py
persistent_cache/decorators.py
persistent_cache/py.typed
persistent_cache/backend/__init__.py
persistent_cache/backend/json.py
persistent_cache/backend/pickle.py
persistent_cache/backend/sqlite.py
persistent_cache/wrappers/__init__.py
persistent_cache_decorator-0.1.10.dist-info/METADATA
persistent_cache_decorator-0.1.10.dist-info/WHEEL
persistent_cache_decorator-0.1.10.dist-info/entry_points.txt
persistent_cache_decorator-0.1.10.dist-info/licenses/LICENSE.txt
persistent_cache_decorator-0.1.10.dist-info/RECORD
